deployer/__init__.py
deployer/checker.py
deployer/cleaner.py
deployer/constants.py
deployer/exceptions.py
deployer/localerefresh.py
deployer/main.py
deployer/push.py
deployer/selfish.py
deployer/submodules.py
deployer/utils.py
gsmu/__init__.py
gsmu/core.py
gsmu/main.py
kuma_deployer-0.2.6.dist-info/METADATA
kuma_deployer-0.2.6.dist-info/WHEEL
kuma_deployer-0.2.6.dist-info/entry_points.txt
kuma_deployer-0.2.6.dist-info/top_level.txt
kuma_deployer-0.2.6.dist-info/RECORD
