Metadata-Version: 2.1
Name: kuma-deployer
Version: 0.2.6
Summary: https://kuma.readthedocs.io/en/latest/deploy.html as a script
Home-page: https://github.com/mdn/kuma-deployer
Author: Peter Bengtsson
Author-email: mail@peterbe.com
License: MPL 2.0
Keywords: git github submodule
Platform: UNKNOWN
Classifier: Programming Language :: Python
Classifier: Programming Language :: Python :: 3
Classifier: Programming Language :: Python :: Implementation :: CPython
Classifier: License :: OSI Approved :: Mozilla Public License 2.0 (MPL 2.0)
Requires-Dist: GitPython
Requires-Dist: click
Requires-Dist: PyGithub
Requires-Dist: python-decouple
Requires-Dist: requests
Provides-Extra: dev
Requires-Dist: black (==19.3b0) ; extra == 'dev'
Requires-Dist: flake8 (==3.7.8) ; extra == 'dev'
Requires-Dist: therapist ; extra == 'dev'
